{
  "id": "cosmos_T28_tracking_18",
  "category": "threats",
  "name": "Tracking 18",
  "description": "Suburban home backyard at midday, viewed from an elevated position under the roofline. Person in various poses: standing straight, bending to pick something up, crouching, reaching overhead, sitting down. Static elevated viewpoint, clear daytime footage. Real-time speed, natural fluid motion at 1x playback rate.",
  "source": "cosmos",
  "scene": {
    "location": "backyard",
    "camera_type": "security_camera",
    "resolution": "720p"
  },
  "environment": {
    "time_of_day": "day",
    "weather": "clear"
  },
  "generation": {
    "format": "video",
    "duration_sec": 5.8,
    "cosmos_prompt": "Suburban home backyard at midday, viewed from an elevated position under the roofline. Person in various poses: standing straight, bending to pick something up, crouching, reaching overhead, sitting down. Static elevated viewpoint, clear daytime footage. Real-time speed, natural fluid motion at 1x playback rate."
  }
}